prediction_runner/__init__.py
prediction_runner/__main__.py
prediction_runner/cli.py
ratcliff_prediction_runner-0.1.1.dist-info/METADATA
ratcliff_prediction_runner-0.1.1.dist-info/WHEEL
ratcliff_prediction_runner-0.1.1.dist-info/entry_points.txt
ratcliff_prediction_runner-0.1.1.dist-info/RECORD
