Metadata-Version: 2.1
Name: ratcliff-prediction-runner
Version: 0.1.1
Summary: 
Author: ryanratcliff
Author-email: ryanrratcliff@gmail.com
Requires-Python: >=3.11,<4.0
Classifier: Programming Language :: Python :: 3
Classifier: Programming Language :: Python :: 3.11
Requires-Dist: black (>=23.7.0,<24.0.0)
Requires-Dist: click (>=8.1.6,<9.0.0)
Requires-Dist: ratcliff-breast-cancer-predictor (>=0.1.2,<0.2.0)
